MedQueryPy/__init__.py
MedQueryPy/fetcher.py
medquerypy-0.2.2.dist-info/entry_points.txt
medquerypy-0.2.2.dist-info/LICENSE
medquerypy-0.2.2.dist-info/METADATA
medquerypy-0.2.2.dist-info/WHEEL
medquerypy-0.2.2.dist-info/RECORD
