Metadata-Version: 2.3
Name: medquerypy
Version: 0.2.2
Summary: A Python tool to fetch research papers from PubMed.
License: MIT
Author: Aditya Srivastav
Author-email: your.email@example.com
Requires-Python: >=3.8,<4.0
Classifier: License :: OSI Approved :: MIT License
Classifier: Programming Language :: Python :: 3
Classifier: Programming Language :: Python :: 3.8
Classifier: Programming Language :: Python :: 3.9
Classifier: Programming Language :: Python :: 3.10
Classifier: Programming Language :: Python :: 3.11
Classifier: Programming Language :: Python :: 3.12
Classifier: Programming Language :: Python :: 3.13
Requires-Dist: pandas (>=2.0.0,<3.0.0)
Requires-Dist: requests (>=2.31.0,<3.0.0)
